fabric_protos_python/__init__.py
fabric_protos_python/common/__init__.py
fabric_protos_python/common/collection_pb2.py
fabric_protos_python/common/collection_pb2_grpc.py
fabric_protos_python/common/common_pb2.py
fabric_protos_python/common/common_pb2_grpc.py
fabric_protos_python/common/configtx_pb2.py
fabric_protos_python/common/configtx_pb2_grpc.py
fabric_protos_python/common/configuration_pb2.py
fabric_protos_python/common/configuration_pb2_grpc.py
fabric_protos_python/common/ledger_pb2.py
fabric_protos_python/common/ledger_pb2_grpc.py
fabric_protos_python/common/policies_pb2.py
fabric_protos_python/common/policies_pb2_grpc.py
fabric_protos_python/discovery/__init__.py
fabric_protos_python/discovery/protocol_pb2.py
fabric_protos_python/discovery/protocol_pb2_grpc.py
fabric_protos_python/gateway/gateway_pb2.py
fabric_protos_python/gateway/gateway_pb2_grpc.py
fabric_protos_python/gossip/__init__.py
fabric_protos_python/gossip/message_pb2.py
fabric_protos_python/gossip/message_pb2_grpc.py
fabric_protos_python/ledger/__init__.py
fabric_protos_python/ledger/queryresult/__init__.py
fabric_protos_python/ledger/queryresult/kv_query_result_pb2.py
fabric_protos_python/ledger/queryresult/kv_query_result_pb2_grpc.py
fabric_protos_python/ledger/rwset/__init__.py
fabric_protos_python/ledger/rwset/kvrwset/__init__.py
fabric_protos_python/ledger/rwset/kvrwset/kv_rwset_pb2.py
fabric_protos_python/ledger/rwset/kvrwset/kv_rwset_pb2_grpc.py
fabric_protos_python/ledger/rwset/rwset_pb2.py
fabric_protos_python/ledger/rwset/rwset_pb2_grpc.py
fabric_protos_python/msp/__init__.py
fabric_protos_python/msp/identities_pb2.py
fabric_protos_python/msp/identities_pb2_grpc.py
fabric_protos_python/msp/msp_config_pb2.py
fabric_protos_python/msp/msp_config_pb2_grpc.py
fabric_protos_python/msp/msp_principal_pb2.py
fabric_protos_python/msp/msp_principal_pb2_grpc.py
fabric_protos_python/orderer/__init__.py
fabric_protos_python/orderer/ab_pb2.py
fabric_protos_python/orderer/ab_pb2_grpc.py
fabric_protos_python-2.5.dist-info/LICENSE
fabric_protos_python-2.5.dist-info/WHEEL
fabric_protos_python-2.5.dist-info/METADATA
fabric_protos_python-2.5.dist-info/RECORD
