Metadata-Version: 2.1
Name: fabric-protos-python
Version: 2.5
Summary: Hyperledger Fabric gRPC and Protocol Buffer Bindings for python
Home-page: https://github.com/ic-matcom/fabric-protos-python
License: Apache
Author: Institute of Cryptography of the Faculty of Mathematics and Computer Science at University of Havana
Author-email: kmilo.denis.glez@yandex.com
Maintainer: Kmilo Denis González
Maintainer-email: kmilo.denis.glez@yandex.com
Requires-Python: >=3.7,<4.0
Classifier: License :: Other/Proprietary License
Classifier: Programming Language :: Python :: 3
Classifier: Programming Language :: Python :: 3.7
Classifier: Programming Language :: Python :: 3.8
Classifier: Programming Language :: Python :: 3.9
Classifier: Programming Language :: Python :: 3.10
Requires-Dist: grpclib (>=0.4.3,<0.5.0)
Requires-Dist: protobuf (>=4.21.7,<5.0.0)
